pyreachx/__init__.py
pyreachx/analyzer.py
pyreachx/cli.py
pyreachx/config.py
pyreachx/reporter.py
pyreachx/result.py
pyreachx-0.1.0.dist-info/LICENSE
pyreachx-0.1.0.dist-info/METADATA
pyreachx-0.1.0.dist-info/WHEEL
pyreachx-0.1.0.dist-info/entry_points.txt
pyreachx-0.1.0.dist-info/top_level.txt
pyreachx-0.1.0.dist-info/RECORD
