Metadata-Version: 2.1
Name: pyreachx
Version: 0.1.0
Summary: Python Code Reachability Analyzer
Home-page: https://github.com/ad3002/pyreachx
Author: Aleksey Komissarov
Author-email: ad3002@gmail.com
Classifier: Development Status :: 3 - Alpha
Classifier: Intended Audience :: Developers
Classifier: Topic :: Software Development :: Testing
Classifier: Programming Language :: Python :: 3
Classifier: Programming Language :: Python :: 3.8
Classifier: Programming Language :: Python :: 3.9
Requires-Python: >=3.8
License-File: LICENSE
Requires-Dist: ast2json>=0.3.0
Requires-Dist: click>=7.0
Requires-Dist: networkx>=2.5
Requires-Dist: jinja2>=2.11.0
Requires-Dist: PyYAML>=5.1.0
Provides-Extra: test
Requires-Dist: pytest>=6.0.0; extra == "test"
Requires-Dist: pytest-cov>=2.0.0; extra == "test"
Requires-Dist: pytest-mock>=3.0.0; extra == "test"
Requires-Dist: black>=21.0; extra == "test"
Requires-Dist: isort>=5.0.0; extra == "test"
Requires-Dist: mypy>=0.900; extra == "test"
Requires-Dist: flake8>=4.0.0; extra == "test"
Requires-Dist: flake8-bugbear>=21.0.0; extra == "test"
Requires-Dist: flake8-docstrings>=1.6.0; extra == "test"
Requires-Dist: flake8-import-order>=0.18.0; extra == "test"
